magicconvert_server/__init__.py
magicconvert_server/server.py
magicconvert_mcp_server-0.1.6.dist-info/METADATA
magicconvert_mcp_server-0.1.6.dist-info/WHEEL
magicconvert_mcp_server-0.1.6.dist-info/entry_points.txt
magicconvert_mcp_server-0.1.6.dist-info/licenses/LICENSE
magicconvert_mcp_server-0.1.6.dist-info/RECORD
