Metadata-Version: 2.4
Name: magicconvert-mcp-server
Version: 0.1.6
Summary: MCP Server for MagicConvert - Convert various file formats to Markdown
Project-URL: Homepage, https://github.com/yourusername/magicconvert-mcp-server
Author-email: Muhammad Noman <muhammadnomanshafiq76@gmail.com>
License: MIT
License-File: LICENSE
Keywords: conversion,docx,markdown,mcp,ocr,pdf,server
Classifier: Development Status :: 4 - Beta
Classifier: Intended Audience :: Developers
Classifier: License :: OSI Approved :: MIT License
Classifier: Programming Language :: Python :: 3
Classifier: Programming Language :: Python :: 3.10
Classifier: Programming Language :: Python :: 3.11
Classifier: Programming Language :: Python :: 3.12
Requires-Python: >=3.10
Requires-Dist: aiofiles>=0.8.0
Requires-Dist: magicconvert
Requires-Dist: mcp>=1.0.0
